solapi/__init__.py
solapi/auth.py
solapi/config.py
solapi/message.py
solapi/request.py
solapi/storage.py
solapi/__pycache__/__init__.cpython-38.pyc
solapi/kakao_talk/__init__.py
solapi/kakao_talk/alim_talk.py
solapi/kakao_talk/template.py
solapi/senders/__init__.py
solapi/senders/message_senders.py
solapi/sms/__init__.py
solapi/sms/base.py
solapi/sms/lms.py
solapi/sms/message.py
solapi/sms/mms.py
solapi/sms/sms.py
solapi/sms/__pycache__/__init__.cpython-38.pyc
solapi/sms/__pycache__/message.cpython-38.pyc
python_solapi_messages-0.1.6.dist-info/LICENSE
python_solapi_messages-0.1.6.dist-info/METADATA
python_solapi_messages-0.1.6.dist-info/WHEEL
python_solapi_messages-0.1.6.dist-info/top_level.txt
python_solapi_messages-0.1.6.dist-info/RECORD
