Metadata-Version: 2.1
Name: python-solapi-messages
Version: 0.1.6
Summary: A Python library for sending messages using SolApi
Home-page: https://github.com/RUNNERS-IM/python-solapi-messages
Author: RUNNERS
Author-email: dev@runners.im
Classifier: Development Status :: 3 - Alpha
Classifier: Intended Audience :: Developers
Classifier: License :: OSI Approved :: MIT License
Classifier: Operating System :: OS Independent
Classifier: Programming Language :: Python :: 3
Classifier: Topic :: Software Development :: Libraries :: Python Modules
Requires-Python: >=3.6
License-File: LICENSE
Requires-Dist: requests>=2.25.1
